JColors/JColors.py
JColors/__init__.py
JColors-0.0.2.dist-info/LICENSE
JColors-0.0.2.dist-info/METADATA
JColors-0.0.2.dist-info/WHEEL
JColors-0.0.2.dist-info/top_level.txt
JColors-0.0.2.dist-info/RECORD
